tir_guardrails/__init__.py
tir_guardrails/constants.py
tir_guardrails/guard.py
tir_guardrails/helpers.py
tir_guardrails/models.py
tir_guardrails/harmful_content/__init__.py
tir_guardrails/harmful_content/prompt_template.py
tir_guardrails/harmful_content/validator.py
tir_guardrails/phrase_filter/__init__.py
tir_guardrails/phrase_filter/validator.py
tir_guardrails/pii_filter/__init__.py
tir_guardrails/pii_filter/validator.py
tir_guardrails/profanity_filter/__init__.py
tir_guardrails/profanity_filter/validator.py
tir_guardrails/word_filter/__init__.py
tir_guardrails/word_filter/validator.py
tir_guardrails-0.0.8.dev0.dist-info/LICENSE
tir_guardrails-0.0.8.dev0.dist-info/METADATA
tir_guardrails-0.0.8.dev0.dist-info/WHEEL
tir_guardrails-0.0.8.dev0.dist-info/top_level.txt
tir_guardrails-0.0.8.dev0.dist-info/RECORD
